{
  "project_info": {
    "project_number": "1036378721618",
    "project_id": "meal-management-7bfc5",
    "storage_bucket": "meal-management-7bfc5.appspot.com"
  },
  "client": [
    {
      "client_info": {
        "mobilesdk_app_id": "1:1036378721618:android:c19f92b86cd34751a7fe8b",
        "android_client_info": {
          "package_name": "com.nishat00.mealmanagement"
        }
      },
      "oauth_client": [
        {
          "client_id": "1036378721618-afl36710142uv345kft8olif8e66foje.apps.googleusercontent.com",
          "client_type": 3
        }
      ],
      "api_key": [
        {
          "current_key": "AIzaSyDL5P0ZaPqbwGHIgJVfIbDchshduC6yo-g"
        }
      ],
      "services": {
        "appinvite_service": {
          "other_platform_oauth_client": [
            {
              "client_id": "1036378721618-afl36710142uv345kft8olif8e66foje.apps.googleusercontent.com",
              "client_type": 3
            }
          ]
        }
      }
    }
  ],
  "configuration_version": "1"
}